pako/__init__.py
pako/__main__.py
pako/config_loader.py
pako/package_format.py
pako/package_manager_data.py
pako/pako_manager.py
pako-0.3.1.data/data/pako/LICENSE
pako-0.3.1.dist-info/LICENSE
pako-0.3.1.dist-info/METADATA
pako-0.3.1.dist-info/WHEEL
pako-0.3.1.dist-info/entry_points.txt
pako-0.3.1.dist-info/top_level.txt
pako-0.3.1.dist-info/RECORD
