Metadata-Version: 2.1
Name: pako
Version: 0.3.1
Summary: The universal package manager library
Home-page: https://github.com/MycroftAI/pako
Author: Mycroft AI
Author-email: support@mycroft.ai
Maintainer: Matthew Scholefield
Maintainer-email: matthew331199@gmail.com
License: Apache-2.0
Platform: UNKNOWN
Classifier: Development Status :: 4 - Beta
Classifier: Intended Audience :: Developers
Classifier: Topic :: Software Development :: Libraries
Classifier: Topic :: System :: Software Distribution
Classifier: License :: OSI Approved :: Apache Software License
Classifier: Programming Language :: Python :: 3.6
Classifier: Programming Language :: Python :: 3.7
Classifier: Programming Language :: Python :: 3.8
Classifier: Programming Language :: Python :: 3.9
Requires-Dist: appdirs
